mt5_trading_lib/__init__.py
mt5_trading_lib/async_client.py
mt5_trading_lib/cache_manager.py
mt5_trading_lib/config.py
mt5_trading_lib/connector.py
mt5_trading_lib/data_fetcher.py
mt5_trading_lib/event_bus.py
mt5_trading_lib/exceptions.py
mt5_trading_lib/logging_config.py
mt5_trading_lib/metrics_collector.py
mt5_trading_lib/middleware.py
mt5_trading_lib/order_manager.py
mt5_trading_lib/retry_manager.py
mt5_trading_lib/security_manager.py
mt5_trading_lib-0.1.1.dist-info/licenses/LICENSE
mt5_trading_lib-0.1.1.dist-info/METADATA
mt5_trading_lib-0.1.1.dist-info/WHEEL
mt5_trading_lib-0.1.1.dist-info/top_level.txt
mt5_trading_lib-0.1.1.dist-info/RECORD
