Metadata-Version: 2.4
Name: mt5-trading-lib
Version: 0.1.1
Summary: Современная Python-библиотека для взаимодействия с MetaTrader5
Author-email: Павел Садовенко <mtrfrgm@gmail.com>
License: MIT
Project-URL: Homepage, https://github.com/paxelcool/MT5_trading_lib_project
Project-URL: Repository, https://github.com/paxelcool/MT5_trading_lib_project
Project-URL: Documentation, https://github.com/paxelcool/MT5_trading_lib_project/blob/main/README.md
Project-URL: Bug Tracker, https://github.com/paxelcool/MT5_trading_lib_project/issues
Keywords: trading,metatrader5,forex,finance
Classifier: Development Status :: 3 - Alpha
Classifier: Intended Audience :: Financial and Insurance Industry
Classifier: License :: OSI Approved :: MIT License
Classifier: Programming Language :: Python :: 3
Classifier: Programming Language :: Python :: 3.8
Classifier: Programming Language :: Python :: 3.9
Classifier: Programming Language :: Python :: 3.10
Classifier: Programming Language :: Python :: 3.11
Classifier: Topic :: Office/Business :: Financial :: Investment
Requires-Python: >=3.8
License-File: LICENSE
Requires-Dist: MetaTrader5; platform_system == "Windows"
Requires-Dist: pandas
Requires-Dist: pydantic
Requires-Dist: pydantic-settings
Requires-Dist: cachetools
Requires-Dist: redis
Requires-Dist: tenacity
Requires-Dist: pybreaker
Requires-Dist: python-dotenv
Requires-Dist: cryptography
Requires-Dist: structlog
Requires-Dist: asyncio-mqtt
Requires-Dist: aioredis
Requires-Dist: prometheus-client
Provides-Extra: dev
Requires-Dist: pytest; extra == "dev"
Requires-Dist: pytest-asyncio; extra == "dev"
Requires-Dist: pytest-cov; extra == "dev"
Requires-Dist: pytest-mock; extra == "dev"
Requires-Dist: mypy; extra == "dev"
Requires-Dist: black; extra == "dev"
Requires-Dist: flake8; extra == "dev"
Requires-Dist: isort; extra == "dev"
Requires-Dist: pre-commit; extra == "dev"
Requires-Dist: build; extra == "dev"
Requires-Dist: twine; extra == "dev"
Requires-Dist: bumpver; extra == "dev"
Provides-Extra: docs
Requires-Dist: sphinx; extra == "docs"
Requires-Dist: sphinx-autodoc-typehints; extra == "docs"
Requires-Dist: sphinx-rtd-theme; extra == "docs"
Provides-Extra: test
Requires-Dist: factory-boy; extra == "test"
Requires-Dist: faker; extra == "test"
Requires-Dist: responses; extra == "test"
Dynamic: license-file
